validation/__init__.py
validation/bigquery.py
validation/common.py
validation/enums.py
validation/validation.py
data_drift_detector_mightyhive-0.0.4.dist-info/LICENSE
data_drift_detector_mightyhive-0.0.4.dist-info/METADATA
data_drift_detector_mightyhive-0.0.4.dist-info/WHEEL
data_drift_detector_mightyhive-0.0.4.dist-info/top_level.txt
data_drift_detector_mightyhive-0.0.4.dist-info/RECORD
