Metadata-Version: 2.1
Name: data-drift-detector-mightyhive
Version: 0.0.4
Summary: A data drift detection and schema validation package
Home-page: https://github.com/superyang713/data-drift-detector/blob/main/README.md
Author: Yang Dai
Author-email: yang.dai@mediamonks.com
License: UNKNOWN
Platform: UNKNOWN
Classifier: Programming Language :: Python :: 3.8
Classifier: License :: OSI Approved :: MIT License
Classifier: Operating System :: OS Independent
Classifier: Topic :: Software Development :: Build Tools
Classifier: Intended Audience :: Developers
Classifier: Development Status :: 3 - Alpha
Requires-Python: ==3.8
License-File: LICENSE
Requires-Dist: tensorflow-data-validation
Requires-Dist: google-cloud-storage
